odoo/addons/event_sale_session/README.rst
odoo/addons/event_sale_session/__init__.py
odoo/addons/event_sale_session/__manifest__.py
odoo/addons/event_sale_session/i18n/es.po
odoo/addons/event_sale_session/i18n/event_sale_session.pot
odoo/addons/event_sale_session/i18n/it.po
odoo/addons/event_sale_session/models/__init__.py
odoo/addons/event_sale_session/models/account_invoice.py
odoo/addons/event_sale_session/models/event_event.py
odoo/addons/event_sale_session/models/event_registration.py
odoo/addons/event_sale_session/models/event_session.py
odoo/addons/event_sale_session/models/sale_order.py
odoo/addons/event_sale_session/readme/CONTRIBUTORS.rst
odoo/addons/event_sale_session/readme/DESCRIPTION.rst
odoo/addons/event_sale_session/readme/USAGE.rst
odoo/addons/event_sale_session/reports/__init__.py
odoo/addons/event_sale_session/reports/sale_report.py
odoo/addons/event_sale_session/reports/sale_report_views.xml
odoo/addons/event_sale_session/security/ir.model.access.csv
odoo/addons/event_sale_session/static/description/icon.png
odoo/addons/event_sale_session/static/description/index.html
odoo/addons/event_sale_session/tests/__init__.py
odoo/addons/event_sale_session/tests/test_event_sale_session.py
odoo/addons/event_sale_session/views/event_session_view.xml
odoo/addons/event_sale_session/views/event_view.xml
odoo/addons/event_sale_session/views/sale_order_views.xml
odoo/addons/event_sale_session/wizard/__init__.py
odoo/addons/event_sale_session/wizard/event_edit_registration.py
odoo/addons/event_sale_session/wizard/event_edit_registration.xml
odoo12_addon_event_sale_session-12.0.1.0.0.99.dev7.dist-info/METADATA
odoo12_addon_event_sale_session-12.0.1.0.0.99.dev7.dist-info/WHEEL
odoo12_addon_event_sale_session-12.0.1.0.0.99.dev7.dist-info/top_level.txt
odoo12_addon_event_sale_session-12.0.1.0.0.99.dev7.dist-info/RECORD
